allauth_cas/__init__.py
allauth_cas/apps.py
allauth_cas/exceptions.py
allauth_cas/providers.py
allauth_cas/signals.py
allauth_cas/urls.py
allauth_cas/views.py
allauth_cas/templates/socialaccount/messages/suggest_caslogout.html
allauth_cas/test/__init__.py
allauth_cas/test/testcases.py
django_allauth_cas-1.0.0.dist-info/METADATA
django_allauth_cas-1.0.0.dist-info/RECORD
django_allauth_cas-1.0.0.dist-info/WHEEL
django_allauth_cas-1.0.0.dist-info/top_level.txt
tests/example/__init__.py
tests/example/provider.py
tests/example/urls.py
tests/example/views.py
