Metadata-Version: 2.1
Name: django-allauth-cas
Version: 1.0.0
Summary: CAS support for django-allauth.
Home-page: https://github.com/aureplop/django-allauth-cas
Author: Aurélien Delobelle
Author-email: aurelien.delobelle@gmail.com
License: MIT
Keywords: django allauth cas authentication
Platform: UNKNOWN
Classifier: Development Status :: 4 - Beta
Classifier: Environment :: Web Environment
Classifier: Framework :: Django
Classifier: Framework :: Django :: 1.8
Classifier: Framework :: Django :: 1.9
Classifier: Framework :: Django :: 1.10
Classifier: Framework :: Django :: 1.11
Classifier: Framework :: Django :: 2.0
Classifier: Intended Audience :: Developers
Classifier: License :: OSI Approved :: MIT License
Classifier: Operating System :: OS Independent
Classifier: Programming Language :: Python
Classifier: Programming Language :: Python :: 2
Classifier: Programming Language :: Python :: 2.7
Classifier: Programming Language :: Python :: 3
Classifier: Programming Language :: Python :: 3.4
Classifier: Programming Language :: Python :: 3.5
Classifier: Programming Language :: Python :: 3.6
Classifier: Topic :: Internet :: WWW/HTTP
Provides-Extra: docs
Provides-Extra: tests
Requires-Dist: django-allauth
Requires-Dist: python-cas
Requires-Dist: six
Provides-Extra: docs
Requires-Dist: sphinx; extra == 'docs'
Provides-Extra: tests
Requires-Dist: tox; extra == 'tests'
